blazingapi/__init__.py
blazingapi/admin.py
blazingapi/app.py
blazingapi/default_settings.py
blazingapi/exceptions.py
blazingapi/middleware.py
blazingapi/permissions.py
blazingapi/request.py
blazingapi/response.py
blazingapi/router.py
blazingapi/server.py
blazingapi/settings.py
blazingapi/auth/__init__.py
blazingapi/auth/exceptions.py
blazingapi/auth/middleware.py
blazingapi/auth/models.py
blazingapi/auth/permissions.py
blazingapi/auth/views.py
blazingapi/orm/__init__.py
blazingapi/orm/engines.py
blazingapi/orm/fields.py
blazingapi/orm/managers.py
blazingapi/orm/models.py
blazingapi/orm/query.py
blazingapi/orm/relationships.py
blazingapi/orm/validators.py
blazingapi/security/__init__.py
blazingapi/security/middleware.py
blazingapi-0.0.45.dist-info/LICENSE
blazingapi-0.0.45.dist-info/METADATA
blazingapi-0.0.45.dist-info/WHEEL
blazingapi-0.0.45.dist-info/entry_points.txt
blazingapi-0.0.45.dist-info/top_level.txt
blazingapi-0.0.45.dist-info/RECORD
