Metadata-Version: 2.1
Name: blazingapi
Version: 0.0.45
Summary: A growing framework for building web applications.
Author: Nuno Lemos
Author-email: nunolemos6zw5@gmail.com
License-File: LICENSE
Requires-Dist: bcrypt
Requires-Dist: click
Requires-Dist: gunicorn
Requires-Dist: jsonschema >=3.2.0
Requires-Dist: psycopg2
Requires-Dist: psycopg2-binary
Requires-Dist: mysql-connector-python
